vistats/__init__.py
vistats/core.py
vistats/test_core.py
vistats/util.py
vistats-0.2.1.dist-info/WHEEL
vistats-0.2.1.dist-info/METADATA
vistats-0.2.1.dist-info/RECORD
