Metadata-Version: 2.1
Name: vistats
Version: 0.2.1
Summary: package of visualization for statistical tests.
Home-page: https://github.com/takato86/vistats
Author: takato86
Author-email: okudo@nii.ac.jp
Requires-Python: >=3.9
Classifier: Programming Language :: Python :: 3
Classifier: Programming Language :: Python :: 3.9
Classifier: Programming Language :: Python :: 3.10
Classifier: Programming Language :: Python :: 3.11
Requires-Dist: ipykernel (>=6.17.1,<7.0.0)
Requires-Dist: matplotlib (>=3.6.2,<4.0.0)
Requires-Dist: numpy (>=1.23.5,<2.0.0)
Requires-Dist: pandas (>=1.5.2,<2.0.0)
Requires-Dist: scipy (>=1.9.3,<2.0.0)
Requires-Dist: seaborn (>=0.12.1,<0.13.0)
Project-URL: Repository, https://github.com/takato86/vistats
